spso/__init__.py
spso/spso.py
spso/version.py
spso/test_functions/__init__.py
spso/test_functions/functions.py
spso-1.0.3.dist-info/LICENSE.md
spso-1.0.3.dist-info/METADATA
spso-1.0.3.dist-info/WHEEL
spso-1.0.3.dist-info/top_level.txt
spso-1.0.3.dist-info/RECORD
