Metadata-Version: 2.1
Name: spso
Version: 1.0.3
Summary: Simple particle swarm optimizer in python
Home-page: http://www.github.com/nicochidt/pythonspo
Author: Nicolas Chiaraviglio
Author-email: nico.chiaraviglio@gmail.com
License: GPL
Platform: UNKNOWN
Classifier: Programming Language :: Python :: 3
Classifier: Development Status :: 5 - Production/Stable
Classifier: License :: OSI Approved :: GNU General Public License (GPL)
Classifier: Environment :: Console
